CHANGELOG
tgedr/dataops/commons/utils_databricks.py
tgedr/dataops/commons/utils_reflection.py
tgedr/dataops/commons/utils_spark.py
tgedr/dataops/etl/etl.py
tgedr/dataops/etl/etl_databricks.py
tgedr/dataops/sink/catalog_sink.py
tgedr/dataops/sink/pandas_df_2_excel_volume_sink.py
tgedr/dataops/sink/sink.py
tgedr/dataops/store/parquet_store.py
tgedr/dataops/store/store.py
tgedr/dataops/validation/abs.py
tgedr/dataops/validation/pandas.py
tgedr/dataops/validation/pyspark.py
tgedr_dataops2-0.0.4.dist-info/METADATA
tgedr_dataops2-0.0.4.dist-info/WHEEL
tgedr_dataops2-0.0.4.dist-info/licenses/LICENSE
tgedr_dataops2-0.0.4.dist-info/RECORD
